setup.py
Zero_Thumbnails.egg-info/PKG-INFO
Zero_Thumbnails.egg-info/SOURCES.txt
Zero_Thumbnails.egg-info/dependency_links.txt
Zero_Thumbnails.egg-info/not-zip-safe
Zero_Thumbnails.egg-info/requires.txt
Zero_Thumbnails.egg-info/top_level.txt
thumbnails/__init__.py
thumbnails/forms.py
thumbnails/methods.py
thumbnails/models.py
thumbnails/tests.py
thumbnails/utils.py
thumbnails/views.py
thumbnails/templatetags/__init__.py
thumbnails/templatetags/thumbnails_tags.py