Metadata-Version: 1.0
Name: Zero-Thumbnails
Version: 0.1.2
Summary: App to add and manage thumbnails into a model
Home-page: http://github.com/mandlaweb/Zero-Thumbnails
Author: Jose Maria Zambrana Arze
Author-email: contact@josezambrana.com
License: apache license v2.0
Keywords: zero thumbnails
Platform: UNKNOWN
